newton_python_testing_libary/__init__.py
newton_python_testing_libary/serializer.py
newton_python_testing_libary-0.1.2.dist-info/METADATA
newton_python_testing_libary-0.1.2.dist-info/WHEEL
newton_python_testing_libary-0.1.2.dist-info/RECORD
