Metadata-Version: 2.1
Name: newton-python-testing-libary
Version: 0.1.2
Summary: 
Author: Drumil Patel
Author-email: drumilpatel720@gmail.com
Requires-Python: >=3.7.0,<4.0.0
Classifier: Programming Language :: Python :: 3
Classifier: Programming Language :: Python :: 3.7
Classifier: Programming Language :: Python :: 3.8
Classifier: Programming Language :: Python :: 3.9
Classifier: Programming Language :: Python :: 3.10
Classifier: Programming Language :: Python :: 3.11
Classifier: Programming Language :: Python :: 3.12
Requires-Dist: numpy (==1.21)
Requires-Dist: setuptools (==62)
